[
  {
    "id": 1,
    "name": "A long-term estimation of biogenic volatile organi",
    "image_count": 11
  },
  {
    "id": 2,
    "name": "A simple method based on the thermal anomaly index",
    "image_count": 10
  },
  {
    "id": 3,
    "name": "Adjoint inversion of Chinese non-methane volatile",
    "image_count": 13
  },
  {
    "id": 4,
    "name": "Air quality changes in China 2013-2020_ Effectiven",
    "image_count": 8
  },
  {
    "id": 5,
    "name": "An improved representation of fire non-methane org",
    "image_count": 12
  },
  {
    "id": 6,
    "name": "Biomass burning emissions estimated with a global",
    "image_count": 11
  },
  {
    "id": 7,
    "name": "Changes in the ozone chemical regime over the cont",
    "image_count": 10
  },
  {
    "id": 8,
    "name": "Comparison of measured and model-calculated real-w",
    "image_count": 9
  },
  {
    "id": 9,
    "name": "Daily Emission Patterns of Coal-Fired Power Plants",
    "image_count": 5
  },
  {
    "id": 10,
    "name": "Development of a database for chemical mechanism a",
    "image_count": 3
  },
  {
    "id": 11,
    "name": "Does energy transition improve air quality_ Eviden",
    "image_count": 3
  },
  {
    "id": 12,
    "name": "Energy growth sources and future energy-saving pot",
    "image_count": 9
  },
  {
    "id": 13,
    "name": "Estimation of biogenic VOC emissions and their cor",
    "image_count": 9
  },
  {
    "id": 14,
    "name": "Estimation of emissions from biomass burning in Ch",
    "image_count": 4
  },
  {
    "id": 15,
    "name": "Evaluation of emission factors for light-duty gaso",
    "image_count": 8
  },
  {
    "id": 16,
    "name": "Exhaust Gas Condensation during Engine Cold Start",
    "image_count": 5
  },
  {
    "id": 17,
    "name": "Extension of an assessment model of ship traffic e",
    "image_count": 12
  },
  {
    "id": 18,
    "name": "First space-based derivation of the global atmosph",
    "image_count": 15
  },
  {
    "id": 19,
    "name": "HTAP_v2.2_ a mosaic of regional and global emissio",
    "image_count": 4
  },
  {
    "id": 20,
    "name": "How the Air Clean Plan and carbon mitigation measu",
    "image_count": 8
  },
  {
    "id": 21,
    "name": "Impact of spatial proxies on the representation of",
    "image_count": 6
  },
  {
    "id": 22,
    "name": "Long-term observations of oxygenated volatile orga",
    "image_count": 7
  },
  {
    "id": 23,
    "name": "MIX_ a mosaic Asian anthropogenic emission invento",
    "image_count": 15
  },
  {
    "id": 24,
    "name": "Mobile measurement of vehicle emission factors in",
    "image_count": 4
  },
  {
    "id": 25,
    "name": "On-road emissions of fine particles and associated",
    "image_count": 6
  },
  {
    "id": 26,
    "name": "Progress of Air Pollution Control in China and Its",
    "image_count": 6
  },
  {
    "id": 27,
    "name": "Quantifying on-road vehicle emissions during traff",
    "image_count": 7
  },
  {
    "id": 28,
    "name": "Quantifying the uncertainties of China's emission",
    "image_count": 5
  },
  {
    "id": 29,
    "name": "Quantifying the uncertainties of a bottom-up emiss",
    "image_count": 5
  },
  {
    "id": 30,
    "name": "Segment-based Volatile Organic Compound Emission C",
    "image_count": 5
  },
  {
    "id": 31,
    "name": "Source apportionment of volatile organic compounds",
    "image_count": 8
  },
  {
    "id": 32,
    "name": "Striking impacts of biomass burning on  PM",
    "image_count": 8
  },
  {
    "id": 33,
    "name": "Volatile organic compound (VOC) emissions and heal",
    "image_count": 6
  },
  {
    "id": 34,
    "name": "一种工业热源提取方法_利用温度特征模板的BP神经网络",
    "image_count": 9
  }
]